LICENSE
MANIFEST.in
README.md
setup.cfg
setup.py
distinfo/__init__.py
distinfo/__main__.py
distinfo/base.py
distinfo/cli.py
distinfo/config.py
distinfo/config.yaml
distinfo/const.py
distinfo/distribution.py
distinfo/monkey.py
distinfo/requirement.py
distinfo/util.py
distinfo.egg-info/PKG-INFO
distinfo.egg-info/SOURCES.txt
distinfo.egg-info/dependency_links.txt
distinfo.egg-info/entry_points.txt
distinfo.egg-info/requires.txt
distinfo.egg-info/top_level.txt
distinfo/collectors/__init__.py
distinfo/collectors/collector.py
distinfo/collectors/distinfo.py
distinfo/collectors/findtests.py
distinfo/collectors/git.py
distinfo/collectors/nose.py
distinfo/collectors/pep518.py
distinfo/collectors/pipfile.py
distinfo/collectors/pipreqs.py
distinfo/collectors/pytest.py
distinfo/collectors/requirementsfile.py
distinfo/collectors/toxini.py
tests/__init__.py
tests/cases.py
tests/conftest.py
tests/functional/__init__.py
tests/functional/cases.py
tests/functional/test_cli.py
tests/unit/__init__.py
tests/unit/cases.py
tests/unit/test_distribution.py
tests/unit/test_requirement.py
tests/unit/test_util.py
tests/unit/collector/__init__.py
tests/unit/collector/cases.py
tests/unit/collector/test_collector.py
tests/unit/collector/test_distinfo.py
tests/unit/collector/test_findtests.py
tests/unit/collector/test_nose.py
tests/unit/collector/test_pep518.py
tests/unit/collector/test_pipfile.py
tests/unit/collector/test_pipreqs.py
tests/unit/collector/test_pytest.py
tests/unit/collector/test_requirementsfile.py
tests/unit/collector/test_toxini.py