Metadata-Version: 2.1
Name: distinfo
Version: 0.2.0
Summary: Extract metadata from Python source distributions
Home-page: https://github.com/0compute/distinfo
Author: Arthur Noel
Author-email: arthur@0compute.net
License: GPL-3.0-or-later
Keywords: packaging,metadata,sdist
Platform: UNKNOWN
Classifier: Development Status :: 3 - Alpha
Classifier: Environment :: Console
Classifier: Intended Audience :: Developers
Classifier: License :: OSI Approved :: GNU General Public License v3 or later (GPLv3+)
Classifier: Operating System :: POSIX
Classifier: Programming Language :: Python :: 3
Classifier: Topic :: Software Development :: Build Tools
Classifier: Topic :: System :: Archiving :: Packaging
Classifier: Topic :: System :: Software Distribution
Provides-Extra: dev
